automlll.py
automlll-0.0.1.dist-info/LICENSE.txt
automlll-0.0.1.dist-info/METADATA
automlll-0.0.1.dist-info/WHEEL
automlll-0.0.1.dist-info/entry_points.txt
automlll-0.0.1.dist-info/top_level.txt
automlll-0.0.1.dist-info/RECORD
