Metadata-Version: 2.1
Name: automlll
Version: 0.0.1
Summary: A Python package for automated feature engineering and machine learning.
Home-page: https://github.com/YashBaravaliya/automll_package
Author: Yash Bravaliya
Author-email: yashbaravaliya206@gmail.com
Keywords: auto ml,no code ml,model
Classifier: Programming Language :: Python :: 3
Classifier: License :: OSI Approved :: MIT License
Classifier: Operating System :: OS Independent
Requires-Python: >3.6
License-File: LICENSE.txt
